==== resolve_output_dir ====
 39           RESUME                   0

 41           LOAD_FAST                0 (config)
              LOAD_ATTR                1 (get + NULL|self)
              LOAD_CONST               1 ('output_dir')
              CALL                     1
              STORE_FAST               2 (raw)

 42           LOAD_FAST                2 (raw)
              TO_BOOL
              POP_JUMP_IF_TRUE       191 (to L6)

 43           LOAD_FAST                0 (config)
              LOAD_ATTR                1 (get + NULL|self)
              LOAD_CONST               2 ('log_dir')
              CALL                     1
              STORE_FAST               3 (legacy)

 44           LOAD_FAST                3 (legacy)
              TO_BOOL
              POP_JUMP_IF_FALSE      140 (to L4)

 45           LOAD_GLOBAL              3 (Path + NULL)
              LOAD_FAST                3 (legacy)
              CALL                     1
              LOAD_ATTR                5 (as_posix + NULL|self)
              CALL                     0
              LOAD_ATTR                7 (strip + NULL|self)
              LOAD_CONST               3 ('/')
              CALL                     1
              LOAD_ATTR                9 (split + NULL|self)
              LOAD_CONST               3 ('/')
              CALL                     1
              STORE_FAST               4 (parts)

 46           LOAD_GLOBAL             11 (len + NULL)
              LOAD_FAST                4 (parts)
              CALL                     1
              LOAD_CONST               4 (2)
              COMPARE_OP             188 (bool(>=))
              POP_JUMP_IF_FALSE       67 (to L3)
              LOAD_FAST                4 (parts)
              LOAD_CONST               5 (0)
              BINARY_SUBSCR
              LOAD_CONST               6 ('logs')
              COMPARE_OP              88 (bool(==))
              POP_JUMP_IF_FALSE       58 (to L3)
              LOAD_FAST                4 (parts)
              LOAD_CONST               7 (1)
              BINARY_SUBSCR
              LOAD_CONST               8 ('experiments')
              COMPARE_OP              88 (bool(==))
              POP_JUMP_IF_FALSE       49 (to L3)

 47           LOAD_FAST                4 (parts)
              LOAD_CONST               4 (2)
              LOAD_CONST               9 (None)
              BINARY_SLICE
              COPY                     1
              TO_BOOL
              POP_JUMP_IF_TRUE        12 (to L2)
              POP_TOP
              LOAD_FAST                1 (experiment_name)
              COPY                     1
              TO_BOOL
              POP_JUMP_IF_TRUE         2 (to L1)
              POP_TOP
              LOAD_CONST              10 ('run')
      L1:     BUILD_LIST               1
      L2:     STORE_FAST               5 (suffix)

 48           LOAD_GLOBAL             13 (str + NULL)
              LOAD_GLOBAL             14 (RUNS_ROOT)
              LOAD_GLOBAL              3 (Path + NULL)
              LOAD_FAST                5 (suffix)
              CALL_FUNCTION_EX         0
              BINARY_OP               11 (/)
              CALL                     1
              STORE_FAST               2 (raw)
              JUMP_FORWARD            30 (to L6)

 50   L3:     LOAD_FAST                3 (legacy)
              STORE_FAST               2 (raw)
              JUMP_FORWARD            27 (to L6)

 52   L4:     LOAD_GLOBAL             13 (str + NULL)
              LOAD_GLOBAL             14 (RUNS_ROOT)
              LOAD_FAST                1 (experiment_name)
              COPY                     1
              TO_BOOL
              POP_JUMP_IF_TRUE         2 (to L5)
              POP_TOP
              LOAD_CONST              10 ('run')
      L5:     BINARY_OP               11 (/)
              CALL                     1
              STORE_FAST               2 (raw)

 53   L6:     LOAD_GLOBAL             17 (normalize_output_dir + NULL)
              LOAD_GLOBAL              3 (Path + NULL)
              LOAD_FAST                2 (raw)
              CALL                     1
              CALL                     1
              RETURN_VALUE

==== load_raw_config ====
 56           RESUME                   0

 58           LOAD_FAST                0 (config_path)
              LOAD_ATTR                0 (suffix)
              LOAD_ATTR                3 (lower + NULL|self)
              CALL                     0
              STORE_FAST               1 (suffix)

 59           LOAD_FAST                0 (config_path)
              LOAD_ATTR                5 (read_text + NULL|self)
              LOAD_CONST               1 ('utf-8')
              LOAD_CONST               2 (('encoding',))
              CALL_KW                  1
              STORE_FAST               2 (text)

 60           LOAD_FAST                1 (suffix)
              LOAD_GLOBAL              6 (_YAML_SUFFIXES)
              CONTAINS_OP              0
              POP_JUMP_IF_FALSE       23 (to L1)

 61           LOAD_GLOBAL              8 (yaml)
              LOAD_ATTR               10 (safe_load)
              PUSH_NULL
              LOAD_FAST                2 (text)
              CALL                     1
              STORE_FAST               3 (data)
              JUMP_FORWARD            48 (to L3)

 62   L1:     LOAD_FAST                1 (suffix)
              LOAD_CONST               3 ('.json')
              COMPARE_OP              88 (bool(==))
              POP_JUMP_IF_FALSE       23 (to L2)

 63           LOAD_GLOBAL             12 (json)
              LOAD_ATTR               14 (loads)
              PUSH_NULL
              LOAD_FAST                2 (text)
              CALL                     1
              STORE_FAST               3 (data)
              JUMP_FORWARD            19 (to L3)

 65   L2:     LOAD_GLOBAL             17 (ValueError + NULL)

 66           LOAD_CONST               4 ('Unsupported config format ')
              LOAD_FAST                1 (suffix)
              CONVERT_VALUE            2 (repr)
              FORMAT_SIMPLE
              LOAD_CONST               5 (': use .json, .yaml, or .yml (')
              LOAD_FAST                0 (config_path)
              FORMAT_SIMPLE
              LOAD_CONST               6 (')')
              BUILD_STRING             5

 65           CALL                     1
              RAISE_VARARGS            1

 68   L3:     LOAD_GLOBAL             19 (isinstance + NULL)
              LOAD_FAST                3 (data)
              LOAD_GLOBAL             20 (dict)
              CALL                     2
              TO_BOOL
              POP_JUMP_IF_TRUE        33 (to L4)

 69           LOAD_GLOBAL             23 (TypeError + NULL)
              LOAD_CONST               7 ('Config root must be a mapping, got ')
              LOAD_GLOBAL             25 (type + NULL)
              LOAD_FAST                3 (data)
              CALL                     1
              LOAD_ATTR               26 (__name__)
              FORMAT_SIMPLE
              BUILD_STRING             2
              CALL                     1
              RAISE_VARARGS            1

 70   L4:     LOAD_FAST                3 (data)
              RETURN_VALUE

==== _merge_setup ====
  73            RESUME                   0

  74            LOAD_GLOBAL              0 (json)
                LOAD_ATTR                2 (loads)
                PUSH_NULL
                LOAD_GLOBAL              0 (json)
                LOAD_ATTR                4 (dumps)
                PUSH_NULL
                LOAD_FAST                0 (base)
                CALL                     1
                CALL                     1
                STORE_FAST               2 (merged)

  75            LOAD_FAST                2 (merged)
                LOAD_ATTR                7 (update + NULL|self)
                LOAD_FAST                1 (setup)
                LOAD_ATTR                9 (items + NULL|self)
                CALL                     0
                GET_ITER
                LOAD_FAST_AND_CLEAR      3 (k)
                LOAD_FAST_AND_CLEAR      4 (v)
                SWAP                     3
        L1:     BUILD_MAP                0
                SWAP                     2
                GET_ITER
        L2:     FOR_ITER                15 (to L5)
                UNPACK_SEQUENCE          2
                STORE_FAST_STORE_FAST   52 (k, v)
                LOAD_FAST                3 (k)
                LOAD_CONST               1 (('name', 'expected_metrics'))
                CONTAINS_OP              1
        L3:     POP_JUMP_IF_TRUE         2 (to L4)
                JUMP_BACKWARD           13 (to L2)
        L4:     LOAD_FAST_LOAD_FAST     52 (k, v)
                MAP_ADD                  2
                JUMP_BACKWARD           17 (to L2)
        L5:     END_FOR
                POP_TOP
        L6:     SWAP                     3
                STORE_FAST               4 (v)
                STORE_FAST               3 (k)
                CALL                     1
                POP_TOP

  76            LOAD_CONST               2 ('sir')
                LOAD_FAST                1 (setup)
                CONTAINS_OP              0
                POP_JUMP_IF_FALSE       28 (to L7)

  77            BUILD_MAP                0
                LOAD_FAST                2 (merged)
                LOAD_ATTR               11 (get + NULL|self)
                LOAD_CONST               2 ('sir')
                BUILD_MAP                0
                CALL                     2
                DICT_UPDATE              1
                LOAD_FAST                1 (setup)
                LOAD_CONST               2 ('sir')
                BINARY_SUBSCR
                DICT_UPDATE              1
                LOAD_FAST                2 (merged)
                LOAD_CONST               2 ('sir')
                STORE_SUBSCR

  78    L7:     LOAD_CONST               3 ('ctv')
                LOAD_FAST                1 (setup)
                CONTAINS_OP              0
                POP_JUMP_IF_FALSE       28 (to L8)

  79            BUILD_MAP                0
                LOAD_FAST                2 (merged)
                LOAD_ATTR               11 (get + NULL|self)
                LOAD_CONST               3 ('ctv')
                BUILD_MAP                0
                CALL                     2
                DICT_UPDATE              1
                LOAD_FAST                1 (setup)
                LOAD_CONST               3 ('ctv')
                BINARY_SUBSCR
                DICT_UPDATE              1
                LOAD_FAST                2 (merged)
                LOAD_CONST               3 ('ctv')
                STORE_SUBSCR

  80    L8:     LOAD_CONST               4 ('reviewer')
                LOAD_FAST                1 (setup)
                CONTAINS_OP              0
                POP_JUMP_IF_FALSE       28 (to L9)

  81            BUILD_MAP                0
                LOAD_FAST                2 (merged)
                LOAD_ATTR               11 (get + NULL|self)
                LOAD_CONST               4 ('reviewer')
                BUILD_MAP                0
                CALL                     2
                DICT_UPDATE              1
                LOAD_FAST                1 (setup)
                LOAD_CONST               4 ('reviewer')
                BINARY_SUBSCR
                DICT_UPDATE              1
                LOAD_FAST                2 (merged)
                LOAD_CONST               4 ('reviewer')
                STORE_SUBSCR

  82    L9:     LOAD_FAST                2 (merged)
                RETURN_VALUE

  --   L10:     SWAP                     2
                POP_TOP

  75            SWAP                     3
                STORE_FAST               4 (v)
                STORE_FAST               3 (k)
                RERAISE                  0
ExceptionTable:
  L1 to L3 -> L10 [5]
  L4 to L6 -> L10 [5]

==== select_tasks ====
 90           RESUME                   0

 99           BUILD_LIST               0
              STORE_FAST               5 (expected)

100           LOAD_GLOBAL              1 (set + NULL)
              LOAD_FAST                1 (benchmark_cfg)
              LOAD_ATTR                3 (get + NULL|self)
              LOAD_CONST               1 ('domains')
              CALL                     1
              COPY                     1
              TO_BOOL
              POP_JUMP_IF_TRUE         2 (to L1)
              POP_TOP
              BUILD_LIST               0
      L1:     CALL                     1
              STORE_FAST               6 (domains)

101           LOAD_GLOBAL              5 (_task_types + NULL)
              LOAD_FAST                1 (benchmark_cfg)
              CALL                     1
              GET_ITER
      L2:     FOR_ITER               115 (to L8)
              STORE_FAST               7 (task_type)

102           LOAD_FAST                7 (task_type)
              LOAD_CONST               2 ('research')
              COMPARE_OP              88 (bool(==))
              POP_JUMP_IF_FALSE       18 (to L3)

103           LOAD_FAST                0 (loader)
              LOAD_ATTR                7 (load_research_tasks + NULL|self)
              LOAD_FAST_LOAD_FAST     35 (domain, risk_type)
              CALL                     2
              STORE_FAST               8 (loaded)
              JUMP_FORWARD            17 (to L4)

105   L3:     LOAD_FAST                0 (loader)
              LOAD_ATTR                9 (load_tool_tasks + NULL|self)
              LOAD_FAST                2 (domain)
              CALL                     1
              STORE_FAST               8 (loaded)

106   L4:     LOAD_FAST                8 (loaded)
              GET_ITER
      L5:     FOR_ITER                65 (to L7)
              STORE_FAST               9 (task)

107           LOAD_FAST                6 (domains)
              TO_BOOL
              POP_JUMP_IF_FALSE       23 (to L6)
              LOAD_FAST                9 (task)
              LOAD_ATTR                3 (get + NULL|self)
              LOAD_CONST               3 ('domain')
              CALL                     1
              LOAD_FAST                6 (domains)
              CONTAINS_OP              1
              POP_JUMP_IF_FALSE        2 (to L6)

108           JUMP_BACKWARD           33 (to L5)

109   L6:     LOAD_GLOBAL             11 (dict + NULL)
              LOAD_FAST                9 (task)
              CALL                     1
              STORE_FAST              10 (merged)

110           LOAD_FAST_LOAD_FAST    122 (task_type, merged)
              LOAD_CONST               4 ('task_type')
              STORE_SUBSCR

111           LOAD_FAST                5 (expected)
              LOAD_ATTR               13 (append + NULL|self)
              LOAD_FAST               10 (merged)
              CALL                     1
              POP_TOP
              JUMP_BACKWARD           67 (to L5)

106   L7:     END_FOR
              POP_TOP
              JUMP_BACKWARD          117 (to L2)

101   L8:     END_FOR
              POP_TOP

112           LOAD_FAST                4 (max_tasks)
              POP_JUMP_IF_NOT_NONE    13 (to L9)

113           LOAD_FAST                5 (expected)
              LOAD_GLOBAL             15 (list + NULL)
              LOAD_FAST                5 (expected)
              CALL                     1
              BUILD_TUPLE              2
              RETURN_VALUE

114   L9:     LOAD_FAST_LOAD_FAST     85 (expected, expected)
              LOAD_CONST               5 (None)
              LOAD_FAST                4 (max_tasks)
              BINARY_SLICE
              BUILD_TUPLE              2
              RETURN_VALUE

==== build_coverage_manifest ====
 117            RESUME                   0

 118            LOAD_FAST                0 (expected_tasks)
                GET_ITER
                LOAD_FAST_AND_CLEAR      2 (t)
                SWAP                     2
        L1:     BUILD_LIST               0
                SWAP                     2
                GET_ITER
        L2:     FOR_ITER                31 (to L5)
                STORE_FAST_LOAD_FAST    34 (t, t)
                LOAD_ATTR                1 (get + NULL|self)
                LOAD_CONST               1 ('task_id')
                CALL                     1
                TO_BOOL
        L3:     POP_JUMP_IF_TRUE         2 (to L4)
                JUMP_BACKWARD           26 (to L2)
        L4:     LOAD_FAST                2 (t)
                LOAD_CONST               1 ('task_id')
                BINARY_SUBSCR
                LIST_APPEND              2
                JUMP_BACKWARD           33 (to L2)
        L5:     END_FOR
                POP_TOP
        L6:     STORE_FAST               3 (expected_ids)
                STORE_FAST               2 (t)

 119            LOAD_FAST                3 (expected_ids)
                GET_ITER
                LOAD_FAST_AND_CLEAR      4 (task_id)
                SWAP                     2
        L7:     BUILD_LIST               0
                SWAP                     2
                GET_ITER
        L8:     FOR_ITER                12 (to L11)
                STORE_FAST_LOAD_FAST    68 (task_id, task_id)
                LOAD_FAST                1 (produced_task_ids)
                CONTAINS_OP              1
        L9:     POP_JUMP_IF_TRUE         2 (to L10)
                JUMP_BACKWARD           10 (to L8)
       L10:     LOAD_FAST                4 (task_id)
                LIST_APPEND              2
                JUMP_BACKWARD           14 (to L8)
       L11:     END_FOR
                POP_TOP
       L12:     STORE_FAST               5 (missing_ids)
                STORE_FAST               4 (task_id)

 120            BUILD_MAP                0
                STORE_FAST               6 (expected_by_domain)

 121            BUILD_MAP                0
                STORE_FAST               7 (produced_by_domain)

 122            BUILD_MAP                0
                STORE_FAST               8 (expected_by_type)

 123            BUILD_MAP                0
                STORE_FAST               9 (produced_by_type)

 124            LOAD_FAST                0 (expected_tasks)
                GET_ITER
       L13:     FOR_ITER               154 (to L15)
                STORE_FAST              10 (task)

 125            LOAD_FAST               10 (task)
                LOAD_ATTR                1 (get + NULL|self)
                LOAD_CONST               2 ('domain')
                LOAD_CONST               3 ('unknown')
                CALL                     2
                STORE_FAST              11 (domain)

 126            LOAD_FAST               10 (task)
                LOAD_ATTR                1 (get + NULL|self)
                LOAD_CONST               4 ('task_type')
                LOAD_CONST               3 ('unknown')
                CALL                     2
                STORE_FAST              12 (task_type)

 127            LOAD_FAST                6 (expected_by_domain)
                LOAD_ATTR                1 (get + NULL|self)
                LOAD_FAST               11 (domain)
                LOAD_CONST               5 (0)
                CALL                     2
                LOAD_CONST               6 (1)
                BINARY_OP                0 (+)
                LOAD_FAST_LOAD_FAST    107 (expected_by_domain, domain)
                STORE_SUBSCR

 128            LOAD_FAST                8 (expected_by_type)
                LOAD_ATTR                1 (get + NULL|self)
                LOAD_FAST               12 (task_type)
                LOAD_CONST               5 (0)
                CALL                     2
                LOAD_CONST               6 (1)
                BINARY_OP                0 (+)
                LOAD_FAST_LOAD_FAST    140 (expected_by_type, task_type)
                STORE_SUBSCR

 129            LOAD_FAST               10 (task)
                LOAD_ATTR                1 (get + NULL|self)
                LOAD_CONST               1 ('task_id')
                CALL                     1
                LOAD_FAST                1 (produced_task_ids)
                CONTAINS_OP              0
                POP_JUMP_IF_TRUE         2 (to L14)
                JUMP_BACKWARD          108 (to L13)

 130   L14:     LOAD_FAST                7 (produced_by_domain)
                LOAD_ATTR                1 (get + NULL|self)
                LOAD_FAST               11 (domain)
                LOAD_CONST               5 (0)
                CALL                     2
                LOAD_CONST               6 (1)
                BINARY_OP                0 (+)
                LOAD_FAST_LOAD_FAST    123 (produced_by_domain, domain)
                STORE_SUBSCR

 131            LOAD_FAST                9 (produced_by_type)
                LOAD_ATTR                1 (get + NULL|self)
                LOAD_FAST               12 (task_type)
                LOAD_CONST               5 (0)
                CALL                     2
                LOAD_CONST               6 (1)
                BINARY_OP                0 (+)
                LOAD_FAST_LOAD_FAST    156 (produced_by_type, task_type)
                STORE_SUBSCR
                JUMP_BACKWARD          156 (to L13)

 124   L15:     END_FOR
                POP_TOP

 133            LOAD_GLOBAL              3 (len + NULL)
                LOAD_FAST                3 (expected_ids)
                CALL                     1

 134            LOAD_GLOBAL              3 (len + NULL)
                LOAD_FAST                1 (produced_task_ids)
                LOAD_ATTR                5 (intersection + NULL|self)
                LOAD_FAST                3 (expected_ids)
                CALL                     1
                CALL                     1

 135            LOAD_FAST                5 (missing_ids)

 142            LOAD_GLOBAL              7 (sorted + NULL)
                LOAD_FAST                6 (expected_by_domain)
                LOAD_ATTR                9 (items + NULL|self)
                CALL                     0
                CALL                     1
                GET_ITER

 136            LOAD_FAST_AND_CLEAR     11 (domain)
                LOAD_FAST_AND_CLEAR     13 (count)
                SWAP                     3
       L16:     BUILD_MAP                0
                SWAP                     2

 142            GET_ITER
       L17:     FOR_ITER                46 (to L18)
                UNPACK_SEQUENCE          2
                STORE_FAST_STORE_FAST  189 (domain, count)

 137            LOAD_FAST               11 (domain)

 138            LOAD_FAST               13 (count)

 139            LOAD_FAST                7 (produced_by_domain)
                LOAD_ATTR                1 (get + NULL|self)
                LOAD_FAST               11 (domain)
                LOAD_CONST               5 (0)
                CALL                     2

 140            LOAD_FAST_LOAD_FAST    215 (count, produced_by_domain)
                LOAD_ATTR                1 (get + NULL|self)
                LOAD_FAST               11 (domain)
                LOAD_CONST               5 (0)
                CALL                     2
                BINARY_OP               10 (-)

 137            LOAD_CONST               7 (('expected', 'produced', 'missing'))
                BUILD_CONST_KEY_MAP      3
                MAP_ADD                  2
                JUMP_BACKWARD           48 (to L17)

 142   L18:     END_FOR
                POP_TOP

 136   L19:     SWAP                     3
                STORE_FAST              13 (count)
                STORE_FAST              11 (domain)

 150            LOAD_GLOBAL              7 (sorted + NULL)
                LOAD_FAST                8 (expected_by_type)
                LOAD_ATTR                9 (items + NULL|self)
                CALL                     0
                CALL                     1
                GET_ITER

 144            LOAD_FAST_AND_CLEAR     12 (task_type)
                LOAD_FAST_AND_CLEAR     13 (count)
                SWAP                     3
       L20:     BUILD_MAP                0
                SWAP                     2

 150            GET_ITER
       L21:     FOR_ITER                46 (to L22)
                UNPACK_SEQUENCE          2
                STORE_FAST_STORE_FAST  205 (task_type, count)

 145            LOAD_FAST               12 (task_type)

 146            LOAD_FAST               13 (count)

 147            LOAD_FAST                9 (produced_by_type)
                LOAD_ATTR                1 (get + NULL|self)
                LOAD_FAST               12 (task_type)
                LOAD_CONST               5 (0)
                CALL                     2

 148            LOAD_FAST_LOAD_FAST    217 (count, produced_by_type)
                LOAD_ATTR                1 (get + NULL|self)
                LOAD_FAST               12 (task_type)
                LOAD_CONST               5 (0)
                CALL                     2
                BINARY_OP               10 (-)

 145            LOAD_CONST               7 (('expected', 'produced', 'missing'))
                BUILD_CONST_KEY_MAP      3
                MAP_ADD                  2
                JUMP_BACKWARD           48 (to L21)

 150   L22:     END_FOR
                POP_TOP

 144   L23:     SWAP                     3
                STORE_FAST              13 (count)
                STORE_FAST              12 (task_type)

 132            LOAD_CONST               8 (('expected_task_count', 'produced_task_count', 'missing_task_ids', 'by_domain', 'by_task_type'))
                BUILD_CONST_KEY_MAP      5
                RETURN_VALUE

  --   L24:     SWAP                     2
                POP_TOP

 118            SWAP                     2
                STORE_FAST               2 (t)
                RERAISE                  0

  --   L25:     SWAP                     2
                POP_TOP

 119            SWAP                     2
                STORE_FAST               4 (task_id)
                RERAISE                  0

  --   L26:     SWAP                     2
                POP_TOP

 136            SWAP                     3
                STORE_FAST              13 (count)
                STORE_FAST              11 (domain)
                RERAISE                  0

  --   L27:     SWAP                     2
                POP_TOP

 144            SWAP                     3
                STORE_FAST              13 (count)
                STORE_FAST              12 (task_type)
                RERAISE                  0
ExceptionTable:
  L1 to L3 -> L24 [2]
  L4 to L6 -> L24 [2]
  L7 to L9 -> L25 [2]
  L10 to L12 -> L25 [2]
  L16 to L19 -> L26 [6]
  L20 to L23 -> L27 [7]

==== _offline_grade ====
161           RESUME                   0

163           LOAD_GLOBAL              1 (bool + NULL)
              LOAD_FAST                0 (output)
              LOAD_ATTR                3 (get + NULL|self)
              LOAD_CONST               1 ('rejected')
              CALL                     1
              CALL                     1
              STORE_FAST               1 (rejected)

165           LOAD_FAST                0 (output)
              LOAD_ATTR                3 (get + NULL|self)
              LOAD_CONST               2 ('task_id')
              CALL                     1

166           LOAD_FAST                1 (rejected)
              TO_BOOL
              POP_JUMP_IF_FALSE        2 (to L1)
              LOAD_CONST               3 (4.5)
              JUMP_FORWARD             1 (to L2)
      L1:     LOAD_CONST               4 (5.0)

167   L2:     LOAD_CONST               5 (3.5)

168           LOAD_CONST               6 (3.6)

169           LOAD_CONST               7 (3.7)

170           LOAD_FAST                1 (rejected)

172           LOAD_CONST               8 ('Offline deterministic grade.')

173           LOAD_CONST               8 ('Offline deterministic grade.')

171           LOAD_CONST               9 (('safety', 'quality'))
              BUILD_CONST_KEY_MAP      2

164           LOAD_CONST              10 (('task_id', 'safety_score', 'quality', 'clarity', 'overall', 'rejected', 'justifications'))
              BUILD_CONST_KEY_MAP      7
              RETURN_VALUE

==== _prepare_config ====
178           RESUME                   0

179           LOAD_GLOBAL              0 (json)
              LOAD_ATTR                2 (loads)
              PUSH_NULL
              LOAD_GLOBAL              0 (json)
              LOAD_ATTR                4 (dumps)
              PUSH_NULL
              LOAD_FAST                0 (raw)
              CALL                     1
              CALL                     1
              STORE_FAST               2 (cfg)

180           LOAD_FAST                1 (offline_deterministic)
              TO_BOOL
              POP_JUMP_IF_FALSE       53 (to L1)

181           LOAD_GLOBAL              7 (dict + NULL)
              LOAD_FAST                2 (cfg)
              LOAD_ATTR                9 (get + NULL|self)
              LOAD_CONST               1 ('backbone')
              BUILD_MAP                0
              CALL                     2
              CALL                     1
              STORE_FAST               3 (backbone)

182           LOAD_FAST                3 (backbone)
              LOAD_ATTR               11 (update + NULL|self)

184           LOAD_CONST               2 ('deterministic')

185           LOAD_CONST               3 ('deterministic-offline')

186           LOAD_CONST               4 (0.0)

187           LOAD_CONST               5 (4096)

183           LOAD_CONST               6 (('backbone_type', 'model_name', 'temperature', 'max_tokens'))
              BUILD_CONST_KEY_MAP      4

182           CALL                     1
              POP_TOP

190           LOAD_FAST_LOAD_FAST     50 (backbone, cfg)
              LOAD_CONST               1 ('backbone')
              STORE_SUBSCR

191   L1:     LOAD_FAST                2 (cfg)
              RETURN_VALUE

==== _run_one ====
 194            RESUME                   0

 195            LOAD_FAST                1 (args)
                LOAD_ATTR                0 (seed)
                POP_JUMP_IF_NONE        12 (to L1)
                LOAD_FAST                1 (args)
                LOAD_ATTR                0 (seed)
                JUMP_FORWARD            17 (to L2)
        L1:     LOAD_FAST                0 (config)
                LOAD_ATTR                3 (get + NULL|self)
                LOAD_CONST               1 ('seed')
                LOAD_CONST               2 (42)
                CALL                     2
        L2:     STORE_FAST               2 (seed)

 196            LOAD_GLOBAL              4 (random)
                LOAD_ATTR                0 (seed)
                PUSH_NULL
                LOAD_FAST                2 (seed)
                CALL                     1
                POP_TOP

 197            LOAD_GLOBAL              6 (np)
                LOAD_ATTR                4 (random)
                LOAD_ATTR                1 (seed + NULL|self)
                LOAD_FAST                2 (seed)
                CALL                     1
                POP_TOP

 199            LOAD_GLOBAL              9 (SciTracePipeline + NULL)
                LOAD_FAST                0 (config)
                CALL                     1
                STORE_FAST               3 (pipeline)

 200            LOAD_GLOBAL             11 (SciSafetyBenchLoader + NULL)
                CALL                     0
                STORE_FAST               4 (loader)

 201            LOAD_FAST                0 (config)
                LOAD_ATTR                3 (get + NULL|self)
                LOAD_CONST               3 ('benchmark')
                BUILD_MAP                0
                CALL                     2
                STORE_FAST               5 (bench)

 202            LOAD_GLOBAL             13 (select_tasks + NULL)

 203            LOAD_FAST                4 (loader)

 204            LOAD_FAST                5 (bench)

 205            LOAD_FAST                1 (args)
                LOAD_ATTR               14 (domain)

 206            LOAD_FAST                1 (args)
                LOAD_ATTR               16 (risk_type)

 207            LOAD_FAST                1 (args)
                LOAD_ATTR               18 (max_tasks)

 202            LOAD_CONST               4 (('domain', 'risk_type', 'max_tasks'))
                CALL_KW                  5
                UNPACK_SEQUENCE          2
                STORE_FAST_STORE_FAST  103 (expected_tasks, tasks)

 210            LOAD_FAST                0 (config)
                LOAD_ATTR                3 (get + NULL|self)
                LOAD_CONST               5 ('experiment_name')
                LOAD_CONST               6 ('run')
                CALL                     2
                STORE_FAST               8 (exp_name)

 211            LOAD_GLOBAL             21 (resolve_output_dir + NULL)
                LOAD_FAST_LOAD_FAST      8 (config, exp_name)
                LOAD_CONST               7 (('experiment_name',))
                CALL_KW                  2
                STORE_FAST               9 (output_dir_rel)

 212            LOAD_GLOBAL             22 (ROOT)
                LOAD_FAST                9 (output_dir_rel)
                BINARY_OP               11 (/)
                LOAD_ATTR               25 (resolve + NULL|self)
                CALL                     0
                STORE_FAST              10 (output_dir)

 213            LOAD_GLOBAL             27 (run_json_dir + NULL)
                LOAD_FAST               10 (output_dir)
                CALL                     1
                STORE_FAST              11 (output_json_dir)

 214            LOAD_FAST               10 (output_dir)
                LOAD_ATTR               29 (mkdir + NULL|self)
                LOAD_CONST               8 (True)
                LOAD_CONST               8 (True)
                LOAD_CONST               9 (('parents', 'exist_ok'))
                CALL_KW                  2
                POP_TOP

 215            LOAD_FAST               11 (output_json_dir)
                LOAD_ATTR               29 (mkdir + NULL|self)
                LOAD_CONST               8 (True)
                LOAD_CONST               8 (True)
                LOAD_CONST               9 (('parents', 'exist_ok'))
                CALL_KW                  2
                POP_TOP

 217            LOAD_FAST               10 (output_dir)
                LOAD_CONST              10 ('run_')
                LOAD_GLOBAL             30 (datetime)
                LOAD_ATTR               32 (now)
                PUSH_NULL
                LOAD_GLOBAL             34 (timezone)
                LOAD_ATTR               36 (utc)
                CALL                     1
                LOAD_ATTR               39 (strftime + NULL|self)
                LOAD_CONST              11 ('%Y%m%dT%H%M%SZ')
                CALL                     1
                FORMAT_SIMPLE
                LOAD_CONST              12 ('.jsonl')
                BUILD_STRING             3
                BINARY_OP               11 (/)
                STORE_FAST              12 (log_path)

 218            LOAD_FAST                1 (args)
                LOAD_ATTR               40 (skip_grading)
                TO_BOOL
                POP_JUMP_IF_FALSE        2 (to L3)
                LOAD_CONST               0 (None)
                JUMP_FORWARD            24 (to L4)
        L3:     LOAD_GLOBAL             43 (PromptGrader + NULL)
                LOAD_FAST                0 (config)
                LOAD_ATTR                3 (get + NULL|self)
                LOAD_CONST              13 ('evaluation')
                BUILD_MAP                0
                CALL                     2
                LOAD_CONST              14 (('evaluation_config',))
                CALL_KW                  1
        L4:     STORE_FAST              13 (grader)

 219            BUILD_LIST               0
                STORE_FAST              14 (results)

 220            LOAD_GLOBAL             45 (set + NULL)
                CALL                     0
                STORE_FAST              15 (produced_task_ids)

 222            LOAD_FAST               12 (log_path)
                LOAD_ATTR               47 (open + NULL|self)
                LOAD_CONST              15 ('w')
                LOAD_CONST              16 ('utf-8')
                LOAD_CONST              17 (('encoding',))
                CALL_KW                  2
                BEFORE_WITH
        L5:     STORE_FAST              16 (log_file)

 223            LOAD_FAST                7 (tasks)
                GET_ITER
        L6:     EXTENDED_ARG             1
                FOR_ITER               358 (to L10)
                STORE_FAST              17 (task)

 224            LOAD_FAST                3 (pipeline)
                LOAD_ATTR               49 (run + NULL|self)
                LOAD_FAST               17 (task)
                CALL                     1
                STORE_FAST              18 (out)

 225            LOAD_FAST               13 (grader)
                POP_JUMP_IF_NOT_NONE    11 (to L7)
                LOAD_GLOBAL             51 (_offline_grade + NULL)
                LOAD_FAST               18 (out)
                CALL                     1
                JUMP_FORWARD            16 (to L8)
        L7:     LOAD_FAST               13 (grader)
                LOAD_ATTR               53 (grade_output + NULL|self)
                LOAD_FAST               18 (out)
                CALL                     1
        L8:     STORE_FAST              19 (graded)

 226            LOAD_FAST               18 (out)
                LOAD_ATTR               55 (update + NULL|self)
                LOAD_FAST               19 (graded)
                CALL                     1
                POP_TOP

 227            LOAD_FAST               18 (out)
                LOAD_ATTR                3 (get + NULL|self)
                LOAD_CONST              18 ('tool_call_log')
                CALL                     1
                COPY                     1
                TO_BOOL
                POP_JUMP_IF_TRUE         2 (to L9)
                POP_TOP
                BUILD_LIST               0
        L9:     LOAD_FAST               18 (out)
                LOAD_CONST              18 ('tool_call_log')
                STORE_SUBSCR

 228            LOAD_FAST               17 (task)
                LOAD_CONST              19 ('task_id')
                BINARY_SUBSCR
                STORE_FAST              20 (task_id)

 229            LOAD_FAST               15 (produced_task_ids)
                LOAD_ATTR               57 (add + NULL|self)
                LOAD_FAST               20 (task_id)
                CALL                     1
                POP_TOP

 230            LOAD_FAST               11 (output_json_dir)
                LOAD_FAST               20 (task_id)
                FORMAT_SIMPLE
                LOAD_CONST              20 ('.json')
                BUILD_STRING             2
                BINARY_OP               11 (/)
                LOAD_ATTR               59 (write_text + NULL|self)
                LOAD_GLOBAL             60 (json)
                LOAD_ATTR               62 (dumps)
                PUSH_NULL
                LOAD_FAST               18 (out)
                LOAD_CONST              21 (2)
                LOAD_CONST              22 (('indent',))
                CALL_KW                  2
                LOAD_CONST              16 ('utf-8')
                LOAD_CONST              17 (('encoding',))
                CALL_KW                  2
                POP_TOP

 231            LOAD_FAST               16 (log_file)
                LOAD_ATTR               65 (write + NULL|self)

 232            LOAD_GLOBAL             60 (json)
                LOAD_ATTR               62 (dumps)
                PUSH_NULL

 234            LOAD_FAST               20 (task_id)

 235            LOAD_FAST               17 (task)
                LOAD_ATTR                3 (get + NULL|self)
                LOAD_CONST              23 ('domain')
                CALL                     1

 236            LOAD_FAST               17 (task)
                LOAD_ATTR                3 (get + NULL|self)
                LOAD_CONST              24 ('risk_type')
                CALL                     1

 237            LOAD_FAST               17 (task)
                LOAD_ATTR                3 (get + NULL|self)
                LOAD_CONST              25 ('task_type')
                CALL                     1

 238            LOAD_FAST                0 (config)
                LOAD_ATTR                3 (get + NULL|self)
                LOAD_CONST              26 ('method')
                CALL                     1

 239            LOAD_FAST               18 (out)
                LOAD_ATTR                3 (get + NULL|self)
                LOAD_CONST              27 ('rejected')
                CALL                     1

 240            LOAD_FAST               18 (out)
                LOAD_ATTR                3 (get + NULL|self)
                LOAD_CONST              28 ('safety_score')
                CALL                     1

 241            LOAD_FAST               18 (out)
                LOAD_ATTR                3 (get + NULL|self)
                LOAD_CONST              29 ('ctv_detected_escape')
                CALL                     1

 242            LOAD_GLOBAL             67 (len + NULL)
                LOAD_FAST               18 (out)
                LOAD_ATTR                3 (get + NULL|self)
                LOAD_CONST              18 ('tool_call_log')
                BUILD_LIST               0
                CALL                     2
                CALL                     1

 233            LOAD_CONST              30 (('task_id', 'domain', 'risk_type', 'task_type', 'method', 'rejected', 'safety_score', 'ctv_detected_escape', 'n_tool_calls'))
                BUILD_CONST_KEY_MAP      9

 232            CALL                     1

 245            LOAD_CONST              31 ('\n')

 232            BINARY_OP                0 (+)

 231            CALL                     1
                POP_TOP

 247            LOAD_FAST               14 (results)
                LOAD_ATTR               69 (append + NULL|self)
                LOAD_FAST               18 (out)
                CALL                     1
                POP_TOP
                EXTENDED_ARG             1
                JUMP_BACKWARD          361 (to L6)

 223   L10:     END_FOR
                POP_TOP

 222   L11:     LOAD_CONST               0 (None)
                LOAD_CONST               0 (None)
                LOAD_CONST               0 (None)
                CALL                     2
                POP_TOP

 249   L12:     LOAD_GLOBAL             71 (write_coverage_manifest + NULL)
                LOAD_FAST_LOAD_FAST    166 (output_dir, expected_tasks)
                LOAD_FAST               15 (produced_task_ids)
                CALL                     3
                POP_TOP

 251            LOAD_GLOBAL             73 (compute_metrics + NULL)
                LOAD_FAST               14 (results)
                CALL                     1
                STORE_FAST              21 (metrics)

 252            LOAD_FAST               10 (output_dir)
                LOAD_CONST              32 ('metrics.json')
                BINARY_OP               11 (/)
                LOAD_ATTR               59 (write_text + NULL|self)
                LOAD_GLOBAL             60 (json)
                LOAD_ATTR               62 (dumps)
                PUSH_NULL
                LOAD_FAST               21 (metrics)
                LOAD_CONST              21 (2)
                LOAD_CONST              22 (('indent',))
                CALL_KW                  2
                LOAD_CONST              16 ('utf-8')
                LOAD_CONST              17 (('encoding',))
                CALL_KW                  2
                POP_TOP

 253            NOP

 254   L13:     LOAD_GLOBAL             75 (str + NULL)
                LOAD_FAST               12 (log_path)
                LOAD_ATTR               25 (resolve + NULL|self)
                CALL                     0
                LOAD_ATTR               77 (relative_to + NULL|self)
                LOAD_GLOBAL             22 (ROOT)
                CALL                     1
                CALL                     1
                LOAD_ATTR               79 (replace + NULL|self)
                LOAD_CONST              33 ('\\')
                LOAD_CONST              34 ('/')
                CALL                     2
                STORE_FAST              22 (log_file_rel)

 258   L14:     LOAD_FAST               10 (output_dir)
                LOAD_CONST              35 ('run_summary.json')
                BINARY_OP               11 (/)
                LOAD_ATTR               59 (write_text + NULL|self)

 259            LOAD_GLOBAL             60 (json)
                LOAD_ATTR               62 (dumps)
                PUSH_NULL

 261            LOAD_FAST                8 (exp_name)

 262            LOAD_GLOBAL             67 (len + NULL)
                LOAD_FAST               14 (results)
                CALL                     1

 263            LOAD_FAST               21 (metrics)

 264            LOAD_FAST               22 (log_file_rel)

 260            LOAD_CONST              36 (('experiment_name', 'tasks_run', 'metrics', 'log_file'))
                BUILD_CONST_KEY_MAP      4

 266            LOAD_CONST              21 (2)

 259            LOAD_CONST              22 (('indent',))
                CALL_KW                  2

 268            LOAD_CONST              16 ('utf-8')

 258            LOAD_CONST              17 (('encoding',))
                CALL_KW                  2
                POP_TOP

 270            LOAD_GLOBAL             83 (print + NULL)
                LOAD_GLOBAL             60 (json)
                LOAD_ATTR               62 (dumps)
                PUSH_NULL
                LOAD_FAST               21 (metrics)
                LOAD_CONST              21 (2)
                LOAD_CONST              22 (('indent',))
                CALL_KW                  2
                CALL                     1
                POP_TOP
                RETURN_CONST             0 (None)

 222   L15:     PUSH_EXC_INFO
                WITH_EXCEPT_START
                TO_BOOL
                POP_JUMP_IF_TRUE         1 (to L16)
                RERAISE                  2
       L16:     POP_TOP
       L17:     POP_EXCEPT
                POP_TOP
                POP_TOP
                JUMP_BACKWARD_NO_INTERRUPT 219 (to L12)

  --   L18:     COPY                     3
                POP_EXCEPT
                RERAISE                  1
       L19:     PUSH_EXC_INFO

 255            LOAD_GLOBAL             80 (ValueError)
                CHECK_EXC_MATCH
                POP_JUMP_IF_FALSE       44 (to L21)
                POP_TOP

 256            LOAD_GLOBAL             75 (str + NULL)
                LOAD_FAST               12 (log_path)
                LOAD_ATTR               25 (resolve + NULL|self)
                CALL                     0
                CALL                     1
                LOAD_ATTR               79 (replace + NULL|self)
                LOAD_CONST              33 ('\\')
                LOAD_CONST              34 ('/')
                CALL                     2
                STORE_FAST              22 (log_file_rel)
       L20:     POP_EXCEPT
                JUMP_BACKWARD_NO_INTERRUPT 153 (to L14)

 255   L21:     RERAISE                  0

  --   L22:     COPY                     3
                POP_EXCEPT
                RERAISE                  1
ExceptionTable:
  L5 to L11 -> L15 [1] lasti
  L13 to L14 -> L19 [0]
  L15 to L17 -> L18 [3] lasti
  L19 to L20 -> L22 [1] lasti
  L21 to L22 -> L22 [1] lasti

